spotipy_pandas/__init__.py
spotipy_pandas/spotipy_pandas.py
spotipy_pandas-0.2.0.dist-info/LICENSE
spotipy_pandas-0.2.0.dist-info/METADATA
spotipy_pandas-0.2.0.dist-info/WHEEL
spotipy_pandas-0.2.0.dist-info/top_level.txt
spotipy_pandas-0.2.0.dist-info/RECORD
