Metadata-Version: 2.1
Name: spotipy-pandas
Version: 0.2.0
Summary: A Spotipy-based Pandas wrapper for Spotify API calls
Home-page: https://github.com/opbenesh/spotipy-pandas
Author: Ben Esh
Keywords: spotify pandas
Classifier: Development Status :: 3 - Alpha
Classifier: Intended Audience :: Developers
Classifier: License :: OSI Approved :: MIT License
Classifier: Programming Language :: Python :: 3.7
Requires-Python: >=3.7
License-File: LICENSE
